skiba/__init__.py
skiba/aggregated_point_extraction.py
skiba/buffer_and_sample.py
skiba/buffer_coordinates.py
skiba/buffer_method.py
skiba/common.py
skiba/foliumcode.py
skiba/geojson_buffering.py
skiba/interactive.py
skiba/ipyleafletcode.py
skiba/point_extraction.py
skiba/skiba.py
skiba-2.4.3.dist-info/licenses/LICENSE
skiba-2.4.3.dist-info/METADATA
skiba-2.4.3.dist-info/WHEEL
skiba-2.4.3.dist-info/entry_points.txt
skiba-2.4.3.dist-info/top_level.txt
skiba-2.4.3.dist-info/RECORD
