Metadata-Version: 2.4
Name: skiba
Version: 2.4.3
Summary: A python package for foresters to query Google Earth Engine data
Author-email: Tara Skiba <tskiba@vols.utk.edu>
License: MIT License
Project-URL: Homepage, https://github.com/taraskiba/skiba
Keywords: skiba
Classifier: Intended Audience :: Developers
Classifier: License :: OSI Approved :: MIT License
Classifier: Natural Language :: English
Classifier: Programming Language :: Python :: 3.9
Classifier: Programming Language :: Python :: 3.10
Classifier: Programming Language :: Python :: 3.11
Classifier: Programming Language :: Python :: 3.12
Requires-Python: >=3.9
License-File: LICENSE
Requires-Dist: folium
Requires-Dist: geemap
Requires-Dist: geopandas
Requires-Dist: ipyleaflet
Requires-Dist: ipywidgets
Requires-Dist: leafmap
Requires-Dist: localtileserver
Requires-Dist: matplotlib
Requires-Dist: numpy
Requires-Dist: pandas
Requires-Dist: pyproj
Requires-Dist: requests
Provides-Extra: all
Requires-Dist: skiba[extra]; extra == "all"
Provides-Extra: extra
Requires-Dist: pandas; extra == "extra"
Dynamic: license-file
